{
  "results": [{
    "title": "The Pit",
    "image": "/static/images/painting/pit-sm.jpg",
    "size": "36in by 48in",
    "id": "pit"
  }, {
    "title": "Storm",
    "image": "/static/images/painting/storm.jpg",
    "size": "36in by 48in",
    "id": "storm"
  }, {
    "title": "Tiger",
    "image": "/static/images/painting/tiger-sm.jpg",
    "size": "36in by 48in",
    "id": "sensorly-whitelabel"
  }, {
    "title": "Sensorly Portal",
    "image": "/static/images/painting/sensorly-portal.png",
    "size": "36in by 48in",
    "id": "sensorly-portal"
  }, {
    "title": "B2B Sensorly",
    "image": "/static/images/painting/b2b-sensorly.png",
    "size": "36in by 48in",
    "id": "b2b-sensorly"
  }, {
    "title": "Map Elements",
    "image": "/static/images/painting/me.png",
    "size": "36in by 48in",
    "id": "me"
  }, {
    "title": "TowerSource",
    "image": "/static/images/painting/ts.png",
    "size": "36in by 48in",
    "id": "ts"
  }, {
    "title": "Signal Insights",
    "image": "/static/images/painting/si.png",
    "size": "36in by 48in",
    "id": "signalinsights"
  }, {
    "title": "NHSPI",
    "image": "/static/images/painting/nhspi.png",
    "size": "36in by 48in",
    "id": "nhspi"
  }, {
    "title": "California Alerts",
    "image": "/static/images/painting/cal.png",
    "size": "36in by 48in",
    "id": "calalerts"
  }, {
    "title": "TravWell",
    "image": "/static/images/painting/travwell.png",
    "size": "36in by 48in",
    "id": "travwell"
  }, {
    "title": "NRC",
    "image": "/static/images/painting/nrc.png",
    "size": "36in by 48in",
    "id": "nrc"
  }]
}
